{"javascript_index.md":"be20b8a4","es6_es6基础知识.md":"d818395a","javascript_call、apply、bind.md":"bbb47d77","javascript_js的基础问题.md":"1c96eb35","javascript_闭包.md":"cbdf574f","javascript_原型和原型链.md":"9f745eb3","javascript_js的数据类型相关问题.md":"1802e51f","javascript_执行上下文.md":"0418e972","vue基础_mvc、mvp、mvvm.md":"a25b21c6","vue原理_vue的双向数据绑定原理.md":"2c67b581","vue原理_vue源码.md":"8c7731a3","vue原理_vue3的数据响应式原理.md":"bc19e61a","vue基础_vue2基础知识.md":"726fe8cc","vue基础_vue3和vue2的区别.md":"87e2d67b","about_index.md":"c820b292","vue核心插件_vuex基础.md":"db7509fd","vue基础_vue3基础.md":"1cb759b3","vue核心插件_vue-router基础.md":"890f2b90","vue核心插件_刷新页面vuex状态丢失.md":"1c73f699","index.md":"4f857451","浏览器原理_cookie、session、token.md":"dc62baa1","vue核心插件_前端路由.md":"9c769e9e","think_index.md":"0839c105"}
